[{"id": 1, "parent_id": null, "title": "Women"}, {"id": 2, "parent_id": null, "title": "Men"}, {"id": 3, "parent_id": 1, "title": "View All"}, {"id": 4, "parent_id": 1, "title": "Dresses"}, {"id": 5, "parent_id": 4, "title": "Midi Dresses"}, {"id": 6, "parent_id": 4, "title": "Short Dresses"}, {"id": 7, "parent_id": 4, "title": "Maxi Dresses"}, {"id": 8, "parent_id": 4, "title": "Party Dresses"}, {"id": 9, "parent_id": 4, "title": "Shirt Dresses"}, {"id": 10, "parent_id": 4, "title": "Cami"}, {"id": 11, "parent_id": 4, "title": "Knitted dresses"}, {"id": 12, "parent_id": 4, "title": "Long Sleeve Dresses"}, {"id": 13, "parent_id": 4, "title": "Linen Dresses"}, {"id": 14, "parent_id": 4, "title": "T-Shirt Dresses"}, {"id": 15, "parent_id": 4, "title": "Denim Dresses"}, {"id": 16, "parent_id": 4, "title": "Bodycon Dresses"}, {"id": 17, "parent_id": 4, "title": "Lace Dresses"}, {"id": 18, "parent_id": 4, "title": "Sequin Dresses"}, {"id": 19, "parent_id": 4, "title": "Wrap Dresses"}, {"id": 20, "parent_id": 4, "title": "Skater Dresses"}, {"id": 21, "parent_id": 4, "title": "Jumper Dresses"}, {"id": 22, "parent_id": 4, "title": "Kaftan Dresses"}, {"id": 23, "parent_id": 1, "title": "Tops"}, {"id": 24, "parent_id": 23, "title": "Collared Tops"}, {"id": 25, "parent_id": 23, "title": "Turtlenecks"}, {"id": 26, "parent_id": 23, "title": "Halter Neck Tops"}, {"id": 27, "parent_id": 23, "title": "Cut Out Tops"}, {"id": 28, "parent_id": 23, "title": "Bralette"}, {"id": 29, "parent_id": 23, "title": "Bandeau"}, {"id": 30, "parent_id": 23, "title": "Puff Sleeve"}, {"id": 31, "parent_id": 23, "title": "Vests"}, {"id": 32, "parent_id": 23, "title": "Short Sleeve"}, {"id": 33, "parent_id": 23, "title": "Long Sleeve"}, {"id": 34, "parent_id": 23, "title": "Crop Tops"}, {"id": 35, "parent_id": 23, "title": "Bodies"}, {"id": 36, "parent_id": 23, "title": "T-shirts"}, {"id": 37, "parent_id": 23, "title": "Graphic Tees & Printed T-Shirts"}, {"id": 38, "parent_id": 1, "title": "Trousers"}, {"id": 39, "parent_id": 38, "title": "High Waisted Trousers"}, {"id": 40, "parent_id": 38, "title": "Joggers"}, {"id": 41, "parent_id": 38, "title": "Leggings"}, {"id": 42, "parent_id": 38, "title": "Smart Trousers"}, {"id": 43, "parent_id": 38, "title": "Chinos & Slacks"}, {"id": 44, "parent_id": 38, "title": "Linen Trousers"}, {"id": 45, "parent_id": 38, "title": "Leather Trousers"}, {"id": 46, "parent_id": 38, "title": "Paperbag Trousers"}, {"id": 47, "parent_id": 38, "title": "Cargo Trousers"}, {"id": 48, "parent_id": 38, "title": "Flared Trousers"}, {"id": 49, "parent_id": 38, "title": "Culottes"}, {"id": 50, "parent_id": 1, "title": "Blazers"}, {"id": 51, "parent_id": 1, "title": "Shoes"}, {"id": 52, "parent_id": 51, "title": "Trainers"}, {"id": 53, "parent_id": 51, "title": "Boots"}, {"id": 54, "parent_id": 51, "title": "Wellington Boots"}, {"id": 55, "parent_id": 51, "title": "Pumps"}, {"id": 56, "parent_id": 51, "title": "Heels"}, {"id": 57, "parent_id": 51, "title": "Ballerinas"}, {"id": 58, "parent_id": 51, "title": "Espadrilles"}, {"id": 59, "parent_id": 51, "title": "Sandals"}, {"id": 60, "parent_id": 51, "title": "Flats"}, {"id": 61, "parent_id": 51, "title": "Mules"}, {"id": 62, "parent_id": 51, "title": "Loafers"}, {"id": 63, "parent_id": 51, "title": "Slip-on"}, {"id": 64, "parent_id": 51, "title": "Flip Flops"}, {"id": 65, "parent_id": 51, "title": "Slippers"}, {"id": 66, "parent_id": 1, "title": "Shirts & Blouses"}, {"id": 67, "parent_id": 66, "title": "Blouses"}, {"id": 68, "parent_id": 66, "title": "Shirts"}, {"id": 69, "parent_id": 66, "title": "Tunics"}, {"id": 70, "parent_id": 66, "title": "Off Shoulder Shirts & Blouses"}, {"id": 71, "parent_id": 66, "title": "Denim shirts"}, {"id": 72, "parent_id": 66, "title": "Linen Shirts"}, {"id": 73, "parent_id": 1, "title": "Swimwear & Beachwear"}, {"id": 74, "parent_id": 73, "title": "Bikini Sets"}, {"id": 75, "parent_id": 73, "title": "Swimsuits"}, {"id": 76, "parent_id": 73, "title": "Beachwear"}, {"id": 77, "parent_id": 1, "title": "Sweatshirts & Hoodies"}, {"id": 78, "parent_id": 77, "title": "Hoodies"}, {"id": 79, "parent_id": 77, "title": "Sweatshirts"}, {"id": 80, "parent_id": 1, "title": "Cardigans & Jumpers"}, {"id": 81, "parent_id": 80, "title": "Cardigans"}, {"id": 82, "parent_id": 80, "title": "Jumpers"}, {"id": 83, "parent_id": 80, "title": "Roll Necks"}, {"id": 84, "parent_id": 80, "title": "Ponchos"}, {"id": 85, "parent_id": 80, "title": "Boleros"}, {"id": 86, "parent_id": 80, "title": "Sweater Vests"}, {"id": 87, "parent_id": 1, "title": "Jackets & Coats"}, {"id": 88, "parent_id": 87, "title": "Jackets"}, {"id": 89, "parent_id": 87, "title": "Coats"}, {"id": 90, "parent_id": 87, "title": "Denim Jackets"}, {"id": 91, "parent_id": 87, "title": "Trench Coats"}, {"id": 92, "parent_id": 87, "title": "Parkas"}, {"id": 93, "parent_id": 87, "title": "Raincoats"}, {"id": 94, "parent_id": 87, "title": "Anoraks"}, {"id": 95, "parent_id": 87, "title": "Gilets"}, {"id": 96, "parent_id": 87, "title": "Leather Jackets"}, {"id": 97, "parent_id": 87, "title": "Shackets"}, {"id": 98, "parent_id": 87, "title": "Bomber Jackets"}, {"id": 99, "parent_id": 87, "title": "Biker Jackets"}, {"id": 100, "parent_id": 87, "title": "Puffer Jackets"}, {"id": 101, "parent_id": 1, "title": "Jeans"}, {"id": 102, "parent_id": 101, "title": "Straight Jeans"}, {"id": 103, "parent_id": 101, "title": "Baggy"}, {"id": 104, "parent_id": 101, "title": "Mom Jeans"}, {"id": 105, "parent_id": 101, "title": "Skinny Jeans"}, {"id": 106, "parent_id": 101, "title": "Wide Leg Jeans"}, {"id": 107, "parent_id": 101, "title": "Loose Jeans"}, {"id": 108, "parent_id": 101, "title": "Flare"}, {"id": 109, "parent_id": 101, "title": "Shaping Jeans"}, {"id": 110, "parent_id": 101, "title": "The Jeans Guide Women"}, {"id": 111, "parent_id": 101, "title": "Bootcut"}, {"id": 112, "parent_id": 101, "title": "Boyfriend Jeans"}, {"id": 113, "parent_id": 1, "title": "Skirts"}, {"id": 114, "parent_id": 113, "title": "Midi Skirts"}, {"id": 115, "parent_id": 113, "title": "Short Skirts"}, {"id": 116, "parent_id": 113, "title": "Maxi Skirts"}, {"id": 117, "parent_id": 113, "title": "Denim Skirts"}, {"id": 118, "parent_id": 113, "title": "High-Waisted Skirts"}, {"id": 119, "parent_id": 113, "title": "Slip Skirts"}, {"id": 120, "parent_id": 113, "title": "Mini Skirts"}, {"id": 121, "parent_id": 113, "title": "Leather Skirts"}, {"id": 122, "parent_id": 113, "title": "Pleated Skirts"}, {"id": 123, "parent_id": 113, "title": "Pencil Skirts"}, {"id": 124, "parent_id": 113, "title": "Skater Skirts"}, {"id": 125, "parent_id": 113, "title": "Wrap Skirts"}, {"id": 126, "parent_id": 1, "title": "Shorts"}, {"id": 127, "parent_id": 126, "title": "Denim Shorts"}, {"id": 128, "parent_id": 126, "title": "High Waisted Shorts"}, {"id": 129, "parent_id": 126, "title": "Cycling Shorts"}, {"id": 130, "parent_id": 126, "title": "Bermudas"}, {"id": 131, "parent_id": 1, "title": "Jumpsuits & Playsuits"}, {"id": 132, "parent_id": 131, "title": "Dungarees"}, {"id": 133, "parent_id": 131, "title": "Jumpsuits"}, {"id": 134, "parent_id": 131, "title": "Playsuits & Rompers"}, {"id": 135, "parent_id": 2, "title": "View All"}, {"id": 136, "parent_id": 2, "title": "T-shirts & Tanks"}, {"id": 137, "parent_id": 136, "title": "Vests"}, {"id": 138, "parent_id": 136, "title": "T-shirts"}, {"id": 139, "parent_id": 136, "title": "Long Sleeve"}, {"id": 140, "parent_id": 136, "title": "Polo"}, {"id": 141, "parent_id": 136, "title": "Basics"}, {"id": 142, "parent_id": 136, "title": "Graphic Tees & Printed T-Shirts"}, {"id": 143, "parent_id": 2, "title": "Hoodies & Sweatshirts"}, {"id": 144, "parent_id": 143, "title": "Hoodies"}, {"id": 145, "parent_id": 143, "title": "Sweatshirts"}, {"id": 146, "parent_id": 2, "title": "Trousers"}, {"id": 147, "parent_id": 146, "title": "Cargo"}, {"id": 148, "parent_id": 146, "title": "Chinos"}, {"id": 149, "parent_id": 146, "title": "Joggers"}, {"id": 150, "parent_id": 146, "title": "Smart"}, {"id": 151, "parent_id": 146, "title": "Linen"}, {"id": 152, "parent_id": 2, "title": "Shirts"}, {"id": 153, "parent_id": 152, "title": "Casual Shirts"}, {"id": 154, "parent_id": 152, "title": "Dressed"}, {"id": 155, "parent_id": 152, "title": "Short Sleeve"}, {"id": 156, "parent_id": 152, "title": "Long Sleeve"}, {"id": 157, "parent_id": 152, "title": "Linen"}, {"id": 158, "parent_id": 152, "title": "Denim"}, {"id": 159, "parent_id": 152, "title": "Checked"}, {"id": 160, "parent_id": 2, "title": "Jeans"}, {"id": 161, "parent_id": 160, "title": "Joggers"}, {"id": 162, "parent_id": 160, "title": "Skinny"}, {"id": 163, "parent_id": 160, "title": "Slim"}, {"id": 164, "parent_id": 160, "title": "Regular Fit"}, {"id": 165, "parent_id": 160, "title": "Relaxed Fit"}, {"id": 166, "parent_id": 160, "title": "Loose Fit"}, {"id": 167, "parent_id": 160, "title": "Straight"}, {"id": 168, "parent_id": 160, "title": "Tapered"}, {"id": 169, "parent_id": 2, "title": "Shorts"}, {"id": 170, "parent_id": 169, "title": "Linen Shorts"}, {"id": 171, "parent_id": 169, "title": "Jogger Shorts"}, {"id": 172, "parent_id": 169, "title": "Jeans Shorts"}, {"id": 173, "parent_id": 169, "title": "Chino Shorts"}, {"id": 174, "parent_id": 169, "title": "Cargo Shorts"}, {"id": 175, "parent_id": 169, "title": "Casual Shorts"}, {"id": 176, "parent_id": 2, "title": "Suits & Blazers"}, {"id": 177, "parent_id": 176, "title": "Waistcoats"}, {"id": 178, "parent_id": 176, "title": "Blazers"}, {"id": 179, "parent_id": 176, "title": "Suits"}, {"id": 180, "parent_id": 176, "title": "Suit Trousers"}, {"id": 181, "parent_id": 176, "title": "Premium Quality"}, {"id": 182, "parent_id": 2, "title": "Jackets & Coats"}, {"id": 183, "parent_id": 182, "title": "Gilets"}, {"id": 184, "parent_id": 182, "title": "Linen"}, {"id": 185, "parent_id": 182, "title": "Outdoor"}, {"id": 186, "parent_id": 182, "title": "Jackets"}, {"id": 187, "parent_id": 182, "title": "Coats"}, {"id": 188, "parent_id": 182, "title": "Bomber Jackets"}, {"id": 189, "parent_id": 182, "title": "Denim Jackets"}, {"id": 190, "parent_id": 182, "title": "Biker Jackets"}, {"id": 191, "parent_id": 182, "title": "Windbreakers"}, {"id": 192, "parent_id": 182, "title": "Puffer Jackets"}, {"id": 193, "parent_id": 182, "title": "Overshirts"}, {"id": 194, "parent_id": 182, "title": "Trench Coats"}, {"id": 195, "parent_id": 2, "title": "Sportswear"}, {"id": 196, "parent_id": 195, "title": "Trousers & Joggers"}, {"id": 197, "parent_id": 195, "title": "Shorts"}, {"id": 198, "parent_id": 195, "title": "Leggings & Tights"}, {"id": 199, "parent_id": 195, "title": "Tops"}, {"id": 200, "parent_id": 195, "title": "Jackets"}, {"id": 201, "parent_id": 195, "title": "Bottoms"}, {"id": 202, "parent_id": 195, "title": "Sports Accessories"}, {"id": 203, "parent_id": 2, "title": "Shoes"}, {"id": 204, "parent_id": 203, "title": "Trainers"}, {"id": 205, "parent_id": 203, "title": "Loafers"}, {"id": 206, "parent_id": 203, "title": "Smart Shoes"}, {"id": 207, "parent_id": 203, "title": "Sandals & Espadrilles"}, {"id": 208, "parent_id": 203, "title": "Flip-Flops"}, {"id": 209, "parent_id": 203, "title": "Boots"}, {"id": 210, "parent_id": 203, "title": "Slippers"}, {"id": 211, "parent_id": 2, "title": "Accessories"}, {"id": 212, "parent_id": 211, "title": "Face masks"}, {"id": 213, "parent_id": 211, "title": "Scarves"}, {"id": 214, "parent_id": 211, "title": "Ties, Bow tie and Handkerchiefs"}, {"id": 215, "parent_id": 211, "title": "Belts & Suspenders"}, {"id": 216, "parent_id": 211, "title": "Bags"}, {"id": 217, "parent_id": 211, "title": "Sunglasses"}, {"id": 218, "parent_id": 211, "title": "Jewellery"}, {"id": 219, "parent_id": 211, "title": "Sports Accessories"}, {"id": 220, "parent_id": 211, "title": "Mobile Accessories"}, {"id": 221, "parent_id": 211, "title": "Hats & Caps"}, {"id": 222, "parent_id": 211, "title": "Gloves"}, {"id": 223, "parent_id": 2, "title": "Swimwear"}, {"id": 224, "parent_id": 2, "title": "Underwear"}, {"id": 225, "parent_id": 224, "title": "Briefs"}, {"id": 226, "parent_id": 224, "title": "Boxers"}, {"id": 227, "parent_id": 224, "title": "Trunks"}, {"id": 228, "parent_id": 2, "title": "Socks"}, {"id": 229, "parent_id": 228, "title": "Sports Socks"}, {"id": 230, "parent_id": 228, "title": "Trainer Socks"}, {"id": 231, "parent_id": 2, "title": "Basics"}, {"id": 232, "parent_id": 231, "title": "T-Shirts"}, {"id": 233, "parent_id": 231, "title": "Tank Tops"}, {"id": 234, "parent_id": 231, "title": "Hoodies & Sweatshirts"}, {"id": 235, "parent_id": 231, "title": "Bottoms"}, {"id": 236, "parent_id": 2, "title": "Cardigans & Jumpers"}, {"id": 237, "parent_id": 236, "title": "Cardigans"}, {"id": 238, "parent_id": 236, "title": "Jumpers"}, {"id": 239, "parent_id": 236, "title": "Turtleneck"}, {"id": 240, "parent_id": 2, "title": "Knitwear"}, {"id": 241, "parent_id": 2, "title": "Nightwear & Loungewear"}, {"id": 242, "parent_id": 241, "title": "Pyjamas"}, {"id": 243, "parent_id": 241, "title": "Dressing gowns"}]